thwAPI/__init__.py
thwAPI/test.py
thwAPI/test_2.py
thwAPI/thw.py
thwAPI-1.1.0.dist-info/LICENSE
thwAPI-1.1.0.dist-info/METADATA
thwAPI-1.1.0.dist-info/WHEEL
thwAPI-1.1.0.dist-info/top_level.txt
thwAPI-1.1.0.dist-info/RECORD
