Metadata-Version: 2.1
Name: thwAPI
Version: 1.1.0
Summary: Keeping Tabs With The Hashnode Writeathon (THW)
Home-page: https://github.com/Ronlin1/THW
Author: Ronnie Atuhaire
Author-email: ronlinx6@gmail.com
License: MIT
Keywords: Hashnode Writeathon Challenges Blogging Tech
Classifier: License :: OSI Approved :: MIT License
Classifier: Programming Language :: Python :: 3
Classifier: Programming Language :: Python :: 3.10
License-File: LICENSE
Requires-Dist: requests
Requires-Dist: progress
